CuSP/__init__.py
CuSP/annealing.py
CuSP/me_forward.py
CuSP/me_inversion.py
CuSP/examples/forward.ipynb
CuSP/examples/inversion.ipynb
cusp-0.1.0.dist-info/licenses/LICENSE
cusp-0.1.0.dist-info/METADATA
cusp-0.1.0.dist-info/WHEEL
cusp-0.1.0.dist-info/top_level.txt
cusp-0.1.0.dist-info/RECORD
